codemode/__init__.py
codemode/docker_assets.py
codemode/cli/__init__.py
codemode/cli/main.py
codemode/config/__init__.py
codemode/config/client_config.py
codemode/config/loader.py
codemode/config/models.py
codemode/config/sidecar_config.py
codemode/core/__init__.py
codemode/core/codemode.py
codemode/core/context.py
codemode/core/correlation.py
codemode/core/executor_client.py
codemode/core/registry.py
codemode/docker/__init__.py
codemode/docker/manager.py
codemode/executor/__init__.py
codemode/executor/models.py
codemode/executor/runner.py
codemode/executor/security.py
codemode/executor/service.py
codemode/grpc/__init__.py
codemode/grpc/server.py
codemode/integrations/__init__.py
codemode/integrations/crewai.py
codemode/protos/__init__.py
codemode/protos/codemode.proto
codemode/protos/codemode_pb2.py
codemode/protos/codemode_pb2_grpc.py
codemode/protos/codemode/protos/codemode_pb2.py
codemode/protos/codemode/protos/codemode_pb2_grpc.py
codemode/tools/__init__.py
codemode/tools/base.py
codemode/tools/meta.py
codemode/tools/schema.py
docker_sidecar/Dockerfile
docker_sidecar/README.md
docker_sidecar/docker-compose.yml
opencodemode-0.2.2.dist-info/METADATA
opencodemode-0.2.2.dist-info/WHEEL
opencodemode-0.2.2.dist-info/entry_points.txt
opencodemode-0.2.2.dist-info/licenses/LICENSE
opencodemode-0.2.2.dist-info/RECORD
