Metadata-Version: 2.4
Name: opencodemode
Version: 0.2.2
Summary: Secure code execution for multi-agent AI systems
Project-URL: Homepage, https://github.com/mldlwizard/code_mode
Project-URL: Documentation, https://github.com/mldlwizard/code_mode#readme
Project-URL: Repository, https://github.com/mldlwizard/code_mode
Project-URL: Issues, https://github.com/mldlwizard/code_mode/issues
Author: codemode contributors
License: MIT
License-File: LICENSE
Keywords: agents,ai,code-execution,crewai,langchain,security
Classifier: Development Status :: 3 - Alpha
Classifier: Intended Audience :: Developers
Classifier: License :: OSI Approved :: MIT License
Classifier: Programming Language :: Python :: 3
Classifier: Programming Language :: Python :: 3.11
Classifier: Programming Language :: Python :: 3.12
Classifier: Programming Language :: Python :: 3.13
Classifier: Topic :: Scientific/Engineering :: Artificial Intelligence
Classifier: Topic :: Software Development :: Libraries :: Python Modules
Requires-Python: <3.14,>=3.11
Requires-Dist: click>=8.1.0
Requires-Dist: fastapi>=0.104.0
Requires-Dist: googleapis-common-protos>=1.63.0
Requires-Dist: grpcio-tools>=1.76.0
Requires-Dist: grpcio>=1.62.0
Requires-Dist: protobuf>=4.25.0
Requires-Dist: pydantic>=2.5.0
Requires-Dist: pyyaml>=6.0.0
Requires-Dist: requests>=2.31.0
Requires-Dist: uvicorn>=0.24.0
Provides-Extra: all
Requires-Dist: crewai>=0.1.0; extra == 'all'
Requires-Dist: langchain-core>=0.1.0; extra == 'all'
Requires-Dist: langchain>=0.1.0; extra == 'all'
Requires-Dist: langgraph>=0.0.1; extra == 'all'
Provides-Extra: crewai
Requires-Dist: crewai>=0.1.0; extra == 'crewai'
Provides-Extra: dev
Requires-Dist: black>=25.11.0; extra == 'dev'
Requires-Dist: httpx>=0.28.1; extra == 'dev'
Requires-Dist: isort>=7.0.0; extra == 'dev'
Requires-Dist: mypy>=1.18.2; extra == 'dev'
Requires-Dist: pre-commit>=4.4.0; extra == 'dev'
Requires-Dist: pytest-asyncio>=1.3.0; extra == 'dev'
Requires-Dist: pytest-cov>=7.0.0; extra == 'dev'
Requires-Dist: pytest>=9.0.1; extra == 'dev'
Requires-Dist: ruff>=0.14.5; extra == 'dev'
Provides-Extra: docker
Requires-Dist: googleapis-common-protos>=1.63.0; extra == 'docker'
Requires-Dist: grpcio>=1.62.0; extra == 'docker'
Requires-Dist: protobuf>=4.25.0; extra == 'docker'
Provides-Extra: langchain
Requires-Dist: langchain-core>=0.1.0; extra == 'langchain'
Requires-Dist: langchain>=0.1.0; extra == 'langchain'
Provides-Extra: langgraph
Requires-Dist: langgraph>=0.0.1; extra == 'langgraph'
